LICENSE
MANIFEST.in
README.rst
setup.py
django_google_oauth.egg-info/PKG-INFO
django_google_oauth.egg-info/SOURCES.txt
django_google_oauth.egg-info/dependency_links.txt
django_google_oauth.egg-info/requires.txt
django_google_oauth.egg-info/top_level.txt
google_oauth/__init__.py
google_oauth/models.py
google_oauth/urls.py
google_oauth/views.py