Metadata-Version: 1.1
Name: django-google-oauth
Version: 1.0.0
Summary: Django Integration for Google+ OAuth2
Home-page: https://bitbucket.org/trik82/django-google-oauth/tree/master
Author: Marco trik Marche
Author-email: marco.marche@gnucoop.com
License: Copyright (c) 2014 Marco trik Marche
